{
  "sadis": {
    "integration": {
      "cache": {
        "enabled": false,
        "maxsize": 50,
        "ttl": "PT0m"
      }
    },
    "entries": [
      {
        "id": "BBSIM_OLT_0",
        "hardwareIdentifier": "0f:f1:ce:c0:ff:ee",
        "nasId": "BBSIMOLT000",
        "uplinkPort": 65536
      },
      {
        "id": "BBSM00000001-1",
        "cTag": 900,
        "sTag": 900,
        "nasPortId": "BBSM00000001-1",
        "circuitId": "BBSM00000001-1",
        "remoteId": "BBSIMOLT000",
        "technologyProfileId": 64,
        "upstreamBandwidthProfile": "Default",
        "downstreamBandwidthProfile": "Default"
      },
      {
        "id": "BBSM00000002-1",
        "cTag": 901,
        "sTag": 900,
        "nasPortId": "BBSM00000002-1",
        "circuitId": "BBSM00000002-1",
        "remoteId": "BBSIMOLT000",
        "technologyProfileId": 64,
        "upstreamBandwidthProfile": "Default",
        "downstreamBandwidthProfile": "Default"
      },
      {
        "id": "BBSM00000101-1",
        "cTag": 902,
        "sTag": 900,
        "nasPortId": "BBSM00000101-1",
        "circuitId": "BBSM00000101-1",
        "remoteId": "BBSIMOLT000",
        "technologyProfileId": 64,
        "upstreamBandwidthProfile": "Default",
        "downstreamBandwidthProfile": "Default"
      },
      {
        "id": "BBSM00000102-1",
        "cTag": 903,
        "sTag": 900,
        "nasPortId": "BBSM00000102-1",
        "circuitId": "BBSM00000102-1",
        "remoteId": "BBSIMOLT000",
        "technologyProfileId": 64,
        "upstreamBandwidthProfile": "Default",
        "downstreamBandwidthProfile": "Default"
      }
    ]
  },
  "bandwidthprofile": {
    "integration": {
      "cache": {
        "enabled": true,
        "maxsize": 40,
        "ttl": "PT1m"
      }
    },
    "entries": [
      {
        "id": "Default",
        "cir": 1000000,
        "cbs": 1001,
        "eir": 1002,
        "ebs": 1003,
        "air": 1004
      }
    ]
  }
}
